marketanalyst/__init__.py
marketanalyst/client.py
marketanalyst-0.2.27.dist-info/LICENSE
marketanalyst-0.2.27.dist-info/METADATA
marketanalyst-0.2.27.dist-info/WHEEL
marketanalyst-0.2.27.dist-info/top_level.txt
marketanalyst-0.2.27.dist-info/RECORD
