Metadata-Version: 2.1
Name: marketanalyst
Version: 0.2.27
Summary: This is wrapper for marketanalyst api
Home-page: https://github.com/agrudgit/python-marketanalyst.git
Author: Sayanta Basu
Author-email: sayanta@agrud.com
License: UNKNOWN
Platform: UNKNOWN
Classifier: Programming Language :: Python :: 3
Classifier: License :: OSI Approved :: MIT License
Classifier: Operating System :: OS Independent
Requires-Python: >=3.6
Requires-Dist: requests
Requires-Dist: pandas
Requires-Dist: numpy
Requires-Dist: websockets
Requires-Dist: websocket-client
Requires-Dist: openpyxl
